.DS_Store
dcclab/DCCExceptions.py
dcclab/__init__.py
dcclab/cafeine.py
dcclab/channel.py
dcclab/channelFloat.py
dcclab/channelInteger.py
dcclab/computeengine.py
dcclab/correlationMatrix.py
dcclab/cziFile.py
dcclab/cziUtil.py
dcclab/dataset.py
dcclab/dbQueries.py
dcclab/image.py
dcclab/imageCollection.py
dcclab/imageFile.py
dcclab/lifFile.py
dcclab/lifReader.py
dcclab/loader.py
dcclab/movieFile.py
dcclab/pathPattern.py
dcclab/tiff2AVI.py
dcclab/timeSeries.py
dcclab/zStack.py
dcclab/database/__init__.py
dcclab/database/cervoDatabase.py
dcclab/database/database.py
dcclab/database/databaseUtilities.py
dcclab/database/labdatadb.py
dcclab/database/pomDatabase.py
dcclab/metadata/__init__.py
dcclab/metadata/metadata.py
dcclab/metadata/cziMetadata/__init__.py
dcclab/metadata/cziMetadata/cziChannel.py
dcclab/metadata/cziMetadata/cziFilter.py
dcclab/metadata/cziMetadata/cziMetadata.py
dcclab/metadata/dtfMetadata/__init__.py
dcclab/metadata/dtfMetadata/dtfMetadata.py
dcclab/metadata/sciMetadata/__init__.py
dcclab/metadata/sciMetadata/sciMetadata.py
dcclab/metadata/txtMetadata/__init__.py
dcclab/metadata/txtMetadata/pdkTXTMetadata.py
dcclab/metadata/txtMetadata/txtMetadata.py
dcclab/metadata/xlsxMetadata/__init__.py
dcclab/metadata/xlsxMetadata/pdkXLSXMetadata.py
dcclab/metadata/xlsxMetadata/xlsxMetadata.py
dcclab/speckleAnalysis/__init__.py
dcclab/speckleAnalysis/autocorrelation.py
dcclab/speckleAnalysis/peakMeasurement.py
dcclab/speckleAnalysis/sourceSimulations.py
dcclab/speckleAnalysis/speckleCaracterization.py
dcclab/speckleAnalysis/speckleFolderAnalysis.py
dcclab/speckleAnalysis/speckleStatsGUI.py
dcclab/speckleAnalysis/speckleStatsReport.py
dcclab/speckleAnalysis/utils.py
dcclab/tests/DCCImageTests.py
dcclab/tests/__init__.py
dcclab/tests/context.py
dcclab/tests/correlationMatrixTest.py
dcclab/tests/cziUtilTests.py
dcclab/tests/env.py
dcclab/tests/testBaseTestClass.py
dcclab/tests/testCZIFile.py
dcclab/tests/testChannelFloat.py
dcclab/tests/testChannelInteger.py
dcclab-1.0.10.dist-info/METADATA
dcclab-1.0.10.dist-info/WHEEL
dcclab-1.0.10.dist-info/top_level.txt
dcclab-1.0.10.dist-info/RECORD
