Metadata-Version: 2.1
Name: dcclab
Version: 1.0.10
Summary: A Python library to read, transform, manipulate images and manage databases
Home-page: https://github.com/DCC-Lab/PyDCCLab
Author: Daniel Côté, Gabriel Genest, Mathieu Fournier, Ludovick Bégin
Author-email: dccote@cervo.ulaval.ca
License: MIT
Keywords: image analysis stack movies
Platform: UNKNOWN
Classifier: Development Status :: 4 - Beta
Classifier: Intended Audience :: Science/Research
Classifier: Intended Audience :: Education
Classifier: Topic :: Scientific/Engineering :: Visualization
Classifier: Topic :: Education
Classifier: License :: OSI Approved :: MIT License
Classifier: Programming Language :: Python
Classifier: Programming Language :: Python :: 3
Classifier: Programming Language :: Python :: 3.7
Classifier: Operating System :: OS Independent
Requires-Python: >=3
Requires-Dist: keyring
Requires-Dist: sshtunnel
Requires-Dist: mysql-connector-python
Requires-Dist: requests
Requires-Dist: matplotlib
Requires-Dist: numpy
Requires-Dist: scikit-image
Requires-Dist: scipy
Requires-Dist: czifile (>=2019.6.18)
Requires-Dist: tifffile
Requires-Dist: read-lif
Requires-Dist: opencv-python
Requires-Dist: xlrd
Requires-Dist: seaborn
Requires-Dist: imagecodecs
Requires-Dist: deprecated
